cultureland/__init__.py
cultureland/_types.py
cultureland/cultureland.py
cultureland/pin.py
cultureland/mTranskey/__init__.py
cultureland/mTranskey/_types.py
cultureland/mTranskey/keypad.py
cultureland/mTranskey/rsa.py
cultureland/mTranskey/seed.py
cultureland/mTranskey/transkey.py
cultureland_py-0.0.8.dist-info/licenses/LICENSE
cultureland_py-0.0.8.dist-info/METADATA
cultureland_py-0.0.8.dist-info/WHEEL
cultureland_py-0.0.8.dist-info/top_level.txt
cultureland_py-0.0.8.dist-info/RECORD
