Metadata-Version: 2.4
Name: cultureland.py
Version: 0.0.8
Summary: 컬쳐랜드 모바일웹을 자동화해주는 비공식 라이브러리입니다.
Author-email: DollarNoob <dollar3795@hotmail.com>
Project-URL: Homepage, https://github.com/DollarNoob/cultureland.py
Project-URL: Issues, https://github.com/DollarNoob/cultureland.py/issues
Classifier: Development Status :: 3 - Alpha
Classifier: License :: OSI Approved :: GNU General Public License v3 (GPLv3)
Classifier: Operating System :: OS Independent
Classifier: Programming Language :: Python :: 3
Requires-Python: >=3.10
License-File: LICENSE
Requires-Dist: beautifulsoup4
Requires-Dist: httpx==0.24.1
Requires-Dist: pillow==11.0.0
Requires-Dist: pycryptodome==3.20.0
Dynamic: license-file
